hydro_integrations/__init__.py
hydro_integrations/aws/__init__.py
hydro_integrations/aws/cloudformation.py
hydro_integrations/aws/exceptions.py
hydro_integrations/aws/helpers.py
hydro_integrations/aws/sagemaker/__init__.py
hydro_integrations/aws/sagemaker/exceptions.py
hydro_integrations/aws/sagemaker/utils.py
hydro_integrations/aws/sagemaker/traffic_shadowing/__init__.py
hydro_integrations/aws/sagemaker/traffic_shadowing/template.yaml
hydro_integrations/aws/sagemaker/traffic_shadowing/traffic_shadowing.py
hydro_integrations-2.3.0.dist-info/METADATA
hydro_integrations-2.3.0.dist-info/WHEEL
hydro_integrations-2.3.0.dist-info/top_level.txt
hydro_integrations-2.3.0.dist-info/RECORD
