Metadata-Version: 2.1
Name: hydro-integrations
Version: 2.3.0
Summary: HydroSDK integrations
Home-page: https://hydrosphere.io/
Author: Hydrospheredata
Author-email: info@hydrosphere.io
License: UNKNOWN
Keywords: hydrosphere hydro serving monitoring sagemaker integrations
Platform: UNKNOWN
Classifier: Programming Language :: Python :: 3
Classifier: Operating System :: OS Independent
Requires-Python: >=3.6
Requires-Dist: boto3 (>=1.12.30)
Requires-Dist: sagemaker (>=1.52.1)
